[
  {
    "id": 1,
    "courseName": "Start Web DeveLopment",
    "rating": 4.5,
    "totalStudents": 1250,
    "courseLength": "12 Hours",
    "whatWillLearn": {
      "first": "Absolute Beginner",
      "second": "Bangla Language",
      "third": "Only known basic of computer"
    },
    "img": "https://shikhun.net/wp-content/uploads/2019/07/basic-web-dev.jpg",
    "courseAuthorName": "Rasel Ahamed",
    "CourseLevel": "Beginner",
    "requirement": "Daily minimum one Video watch"
  },
  {
    "id": 2,
    "courseName": "Learn BootStrap",
    "rating": 5,
    "totalStudents": 2900,
    "courseLength": "45 Hours",
    "whatWillLearn": {
      "first": "Bootstap 4 and 5 knowledge",
      "second": "Typing speed good",
      "third": "Experience with any design convert HTML"
    },
    "img": "https://shikhun.net/wp-content/uploads/2019/07/one-fifty.jpg",
    "courseAuthorName": "Golam Rabbani",
    "CourseLevel": "Intermediate",
    "requirement": "Learn how to work code editor"
  },
  {
    "id": 3,
    "courseName": "PSD to HTML",
    "rating": 5,
    "totalStudents": 2354,
    "courseLength": "20 Hours",
    "img": "https://shikhun.net/wp-content/uploads/2019/07/psd-to-html.jpg",
    "courseAuthorName": "Zonayed Ahamed",
    "CourseLevel": "Intermediate",
    "requirement": "Learn how to work code editor"
  },
  {
    "id": 4,
    "courseName": "Learn Javascript and React",
    "rating": 5,
    "totalStudents": 2900,
    "courseLength": "45 Hours",
    "whatWillLearn": {
      "first": "Start javascript of first programming Language",
      "second": "Absolute Beginner",
      "third": "Start JavaScript with basic",
      "fouth": "Also learn React"
    },
    "img": "https://shikhun.net/wp-content/uploads/2019/07/js.jpg",
    "courseAuthorName": "Ali Hosain",
    "CourseLevel": "Intermediate",
    "requirement": "Learn how to work code editor"
  },
  {
    "id": 5,
    "courseName": "Basic PHP",
    "rating": 4.75,
    "totalStudents": 1894,
    "courseLength": "5 Hours",
    "whatWillLearn": {
      "first": "Learn PHP Basic",
      "second": "Absolute Beginner"
    },
    "img": "https://shikhun.net/wp-content/uploads/2019/07/php-basica.jpg",
    "courseAuthorName": "Jhankar Mahabub",
    "CourseLevel": "Intermediate",
    "requirement": "Learn how to work programming language"
  },
  {
    "id": 6,
    "courseName": "Basic Laravel and Projects",
    "rating": 5,
    "totalStudents": 1787,
    "courseLength": "15 Hours",
    "whatWillLearn": {
      "first": "Learn PHP Basic",
      "second": "Absolute Beginner",
      "third": "Basic design sense",
      "fouth": "Brew/Choco Install",
      "five": "PHP OOP"
    },
    "img": "https://shikhun.net/wp-content/uploads/2020/05/b-1.jpg",
    "courseAuthorName": "Sumit Saha",
    "CourseLevel": "Intermediate",
    "requirement": "Install PHP Composer"
  },
  {
    "id": 7,
    "courseName": "Shopify Theme Development",
    "rating": 4.57,
    "totalStudents": 1787,
    "courseLength": "5 Hours",
    "whatWillLearn": {
      "first": "Basic Shopify Structure",
      "second": "Known Shopify Interface"
    },
    "img": "https://shikhun.net/wp-content/uploads/2019/07/shipify.jpg",
    "courseAuthorName": "HM Nayem ",
    "CourseLevel": "Intermediate",
    "requirement": "HTML, CSS, JQuery"
  },
  {
    "id": 8,
    "courseName": "Basic Theme Development",
    "rating": 4.71,
    "totalStudents": 1975,
    "courseLength": "25 Hours",
    "whatWillLearn": {
      "first": "Basic Wordpress theme Structure",
      "second": "Known Wordpress Interface"
    },
    "img": "https://shikhun.net/wp-content/uploads/2019/07/wp-basic.jpg",
    "courseAuthorName": "Abdullah Nahaiyan ",
    "CourseLevel": "Intermediate",
    "requirement": "Advanced HTML & CSS, JQuery, Basic PHP"
  },
  {
    "id": 9,
    "courseName": "Wordpress Malware",
    "rating": 5,
    "totalStudents": 1478,
    "courseLength": "25 Hours",
    "whatWillLearn": {
      "first": "Return Website from hacker",
      "second": "why site hack?"
    },
    "img": "https://shikhun.net/wp-content/uploads/2019/07/maxresdefault-1.jpg",
    "courseAuthorName": "Rasel Ahamed",
    "CourseLevel": "Intermediate",
    "requirement": "Advanced Wordpress Developer"
  }
]
